{
  "success": true,
  "games": [
    {
      "id": "401772911",
      "homeTeam": "Giants",
      "awayTeam": "Vikings",
      "homeScore": 13,
      "awayScore": 16,
      "excitement": 9.1,
      "breakdown": {
        "uncertainty": 8.184948208106997,
        "drama": 8.312317208197104,
        "finish": 10
      },
      "overtime": false
    },
    {
      "id": "401772806",
      "homeTeam": "Lions",
      "awayTeam": "Steelers",
      "homeScore": 24,
      "awayScore": 29,
      "excitement": 9.1,
      "breakdown": {
        "uncertainty": 6.576186649044512,
        "drama": 9.98155281391092,
        "finish": 9.958333333333334
      },
      "overtime": false
    },
    {
      "id": "401772949",
      "homeTeam": "Seahawks",
      "awayTeam": "Rams",
      "homeScore": 38,
      "awayScore": 37,
      "excitement": 8.9,
      "breakdown": {
        "uncertainty": 7.226778022920537,
        "drama": 10,
        "finish": 6.666666666666667
      },
      "overtime": true
    },
    {
      "id": "401772804",
      "homeTeam": "Ravens",
      "awayTeam": "Patriots",
      "homeScore": 24,
      "awayScore": 28,
      "excitement": 8.9,
      "breakdown": {
        "uncertainty": 6.954086531641243,
        "drama": 8.432108128659753,
        "finish": 10
      },
      "overtime": false
    },
    {
      "id": "401772914",
      "homeTeam": "Cardinals",
      "awayTeam": "Falcons",
      "homeScore": 19,
      "awayScore": 26,
      "excitement": 8.8,
      "breakdown": {
        "uncertainty": 6.511809660399425,
        "drama": 7.999414922288683,
        "finish": 10
      },
      "overtime": false
    },
    {
      "id": "401772910",
      "homeTeam": "Cowboys",
      "awayTeam": "Chargers",
      "homeScore": 17,
      "awayScore": 34,
      "excitement": 8.5,
      "breakdown": {
        "uncertainty": 6.342117184845435,
        "drama": 6.683024808868421,
        "finish": 10
      },
      "overtime": false
    },
    {
      "id": "401772913",
      "homeTeam": "Broncos",
      "awayTeam": "Jaguars",
      "homeScore": 20,
      "awayScore": 34,
      "excitement": 8.5,
      "breakdown": {
        "uncertainty": 5.927034483884343,
        "drama": 7.238899339094674,
        "finish": 10
      },
      "overtime": false
    },
    {
      "id": "401772612",
      "homeTeam": "Commanders",
      "awayTeam": "Eagles",
      "homeScore": 18,
      "awayScore": 29,
      "excitement": 8.4,
      "breakdown": {
        "uncertainty": 6.110977097301755,
        "drama": 6.658580947576457,
        "finish": 10
      },
      "overtime": false
    },
    {
      "id": "401772912",
      "homeTeam": "Panthers",
      "awayTeam": "Buccaneers",
      "homeScore": 23,
      "awayScore": 20,
      "excitement": 8.2,
      "breakdown": {
        "uncertainty": 7.959584748355711,
        "drama": 8.936996738153457,
        "finish": 6.033333333333334
      },
      "overtime": false
    },
    {
      "id": "401772613",
      "homeTeam": "Bears",
      "awayTeam": "Packers",
      "homeScore": 22,
      "awayScore": 16,
      "excitement": 8,
      "breakdown": {
        "uncertainty": 5.920545129531266,
        "drama": 7.931572924927639,
        "finish": 5.913333333333334
      },
      "overtime": true
    },
    {
      "id": "401772824",
      "homeTeam": "Colts",
      "awayTeam": "49ers",
      "homeScore": 27,
      "awayScore": 48,
      "excitement": 7.7,
      "breakdown": {
        "uncertainty": 4.432081472917015,
        "drama": 5.266398847217203,
        "finish": 10
      },
      "overtime": false
    },
    {
      "id": "401772934",
      "homeTeam": "Dolphins",
      "awayTeam": "Bengals",
      "homeScore": 21,
      "awayScore": 45,
      "excitement": 7.5,
      "breakdown": {
        "uncertainty": 4.326328822558629,
        "drama": 4.972835984212739,
        "finish": 9.998000000000001
      },
      "overtime": false
    },
    {
      "id": "401772802",
      "homeTeam": "Browns",
      "awayTeam": "Bills",
      "homeScore": 20,
      "awayScore": 23,
      "excitement": 7.1,
      "breakdown": {
        "uncertainty": 3.7261330837356823,
        "drama": 4.28113126932557,
        "finish": 10
      },
      "overtime": false
    },
    {
      "id": "401772803",
      "homeTeam": "Titans",
      "awayTeam": "Chiefs",
      "homeScore": 26,
      "awayScore": 9,
      "excitement": 5.2,
      "breakdown": {
        "uncertainty": 6.067382205800347,
        "drama": 6.740470557128125,
        "finish": 2.2153333333333345
      },
      "overtime": false
    },
    {
      "id": "401772805",
      "homeTeam": "Texans",
      "awayTeam": "Raiders",
      "homeScore": 23,
      "awayScore": 21,
      "excitement": 4.8,
      "breakdown": {
        "uncertainty": 4.4520600558850045,
        "drama": 5.739727844059428,
        "finish": 3.3333333333333335
      },
      "overtime": false
    },
    {
      "id": "401772801",
      "homeTeam": "Saints",
      "awayTeam": "Jets",
      "homeScore": 29,
      "awayScore": 6,
      "excitement": 3.3,
      "breakdown": {
        "uncertainty": 4.167014659763506,
        "drama": 4.78080552669628,
        "finish": 0.9006666666666682
      },
      "overtime": false
    }
  ],
  "metadata": {
    "sport": "NFL",
    "season": 2025,
    "count": 16,
    "totalGames": 16,
    "insufficientData": 0,
    "generatedAt": "2026-01-01T23:24:36.710Z",
    "source": "ESPN Win Probability Analysis",
    "week": 16
  }
}