{
  "success": true,
  "games": [
    {
      "id": "401812677",
      "homeTeam": "Warriors",
      "awayTeam": "Lakers",
      "homeScore": 111,
      "awayScore": 103,
      "excitement": 7.2,
      "breakdown": {
        "tension": 8.272005428786288,
        "drama": 9.23082581281052,
        "finish": 2.1888282304052082
      },
      "overtime": false,
      "bowlName": null,
      "playoffRound": null
    },
    {
      "id": "401812676",
      "homeTeam": "Hornets",
      "awayTeam": "Thunder",
      "homeScore": 114,
      "awayScore": 135,
      "excitement": 5,
      "breakdown": {
        "tension": 4.793648472623708,
        "drama": 6.788343397975027,
        "finish": 1.6398522243326015
      },
      "overtime": false,
      "bowlName": null,
      "playoffRound": null
    }
  ],
  "metadata": {
    "sport": "NBA",
    "season": 2025,
    "count": 2,
    "totalGames": 2,
    "insufficientData": 0,
    "generatedAt": "2026-01-09T22:32:49.503Z",
    "algorithmVersion": "2.5",
    "source": "ESPN Win Probability Analysis",
    "date": "2025-10-05"
  }
}