{
  "success": true,
  "games": [
    {
      "id": "401810234",
      "homeTeam": "Jazz",
      "awayTeam": "Lakers",
      "homeScore": 135,
      "awayScore": 143,
      "excitement": 9,
      "breakdown": {
        "tension": 9.474028808181492,
        "drama": 9.03948561035584,
        "finish": 9.768325170639585
      },
      "overtime": false,
      "bowlName": null,
      "playoffRound": null
    },
    {
      "id": "401810227",
      "homeTeam": "Pacers",
      "awayTeam": "Knicks",
      "homeScore": 113,
      "awayScore": 114,
      "excitement": 8.7,
      "breakdown": {
        "tension": 9.255830220226201,
        "drama": 8.450946270267492,
        "finish": 6.72564549738592
      },
      "overtime": false,
      "bowlName": null,
      "playoffRound": null
    },
    {
      "id": "401810235",
      "homeTeam": "Trail Blazers",
      "awayTeam": "Kings",
      "homeScore": 134,
      "awayScore": 133,
      "excitement": 8.5,
      "breakdown": {
        "tension": 8.505999063352816,
        "drama": 7.875712606172897,
        "finish": 6.545956166733307
      },
      "overtime": true,
      "bowlName": null,
      "playoffRound": null
    },
    {
      "id": "401810231",
      "homeTeam": "Mavericks",
      "awayTeam": "Pistons",
      "homeScore": 116,
      "awayScore": 114,
      "excitement": 8.3,
      "breakdown": {
        "tension": 7.655221111705898,
        "drama": 7.445444274919142,
        "finish": 4.646579013787763
      },
      "overtime": true,
      "bowlName": null,
      "playoffRound": null
    },
    {
      "id": "401810233",
      "homeTeam": "Suns",
      "awayTeam": "Warriors",
      "homeScore": 99,
      "awayScore": 98,
      "excitement": 7.8,
      "breakdown": {
        "tension": 7.950464232398298,
        "drama": 6.765086635945049,
        "finish": 5.667873360277088
      },
      "overtime": false,
      "bowlName": null,
      "playoffRound": null
    },
    {
      "id": "401810229",
      "homeTeam": "Bucks",
      "awayTeam": "Raptors",
      "homeScore": 105,
      "awayScore": 111,
      "excitement": 7.5,
      "breakdown": {
        "tension": 6.053258252953558,
        "drama": 6.995408238663244,
        "finish": 6.332634160856433
      },
      "overtime": false,
      "bowlName": null,
      "playoffRound": null
    },
    {
      "id": "401810228",
      "homeTeam": "Nets",
      "awayTeam": "Heat",
      "homeScore": 95,
      "awayScore": 106,
      "excitement": 6.8,
      "breakdown": {
        "tension": 5.651978417371515,
        "drama": 6.577983402506857,
        "finish": 6.5104489610739025
      },
      "overtime": false,
      "bowlName": null,
      "playoffRound": null
    },
    {
      "id": "401810232",
      "homeTeam": "Nuggets",
      "awayTeam": "Magic",
      "homeScore": 126,
      "awayScore": 115,
      "excitement": 6.7,
      "breakdown": {
        "tension": 6.618672690915641,
        "drama": 8.173508102506755,
        "finish": 2.9106601917664285
      },
      "overtime": false,
      "bowlName": null,
      "playoffRound": null
    },
    {
      "id": "401810230",
      "homeTeam": "Pelicans",
      "awayTeam": "Rockets",
      "homeScore": 133,
      "awayScore": 128,
      "excitement": 6,
      "breakdown": {
        "tension": 2,
        "drama": 2.9506239378261263,
        "finish": 2.4430478150008756
      },
      "overtime": true,
      "bowlName": null,
      "playoffRound": null
    },
    {
      "id": "401810226",
      "homeTeam": "Hornets",
      "awayTeam": "Hawks",
      "homeScore": 133,
      "awayScore": 126,
      "excitement": 5.9,
      "breakdown": {
        "tension": 4.696528447858689,
        "drama": 6.1821620710470935,
        "finish": 4.043297037400471
      },
      "overtime": false,
      "bowlName": null,
      "playoffRound": null
    },
    {
      "id": "401810224",
      "homeTeam": "Thunder",
      "awayTeam": "Clippers",
      "homeScore": 122,
      "awayScore": 101,
      "excitement": 3.2,
      "breakdown": {
        "tension": 0,
        "drama": 2.4811409746236675,
        "finish": 3.625102219988059
      },
      "overtime": false,
      "bowlName": null,
      "playoffRound": null
    },
    {
      "id": "401810225",
      "homeTeam": "Spurs",
      "awayTeam": "Wizards",
      "homeScore": 119,
      "awayScore": 94,
      "excitement": 2.962367588622966,
      "breakdown": {
        "tension": 0.028042239786099765,
        "drama": 1.7913598060744487,
        "finish": 3.348031768596434
      },
      "overtime": false,
      "bowlName": null,
      "playoffRound": null
    }
  ],
  "metadata": {
    "sport": "NBA",
    "season": 2025,
    "count": 12,
    "totalGames": 12,
    "insufficientData": 0,
    "generatedAt": "2026-01-10T04:30:40.266Z",
    "algorithmVersion": "3.0",
    "source": "ESPN Win Probability Analysis",
    "date": "2025-12-18"
  }
}