{
  "success": true,
  "games": [
    {
      "id": "401810049",
      "homeTeam": "Grizzlies",
      "awayTeam": "Thunder",
      "homeScore": 100,
      "awayScore": 114,
      "excitement": 9,
      "breakdown": {
        "uncertainty": 9.507555228932178,
        "drama": 7.278138022389429,
        "finish": 5.158156520954276
      },
      "overtime": false,
      "bowlName": null,
      "playoffRound": null
    },
    {
      "id": "401810046",
      "homeTeam": "Bucks",
      "awayTeam": "Rockets",
      "homeScore": 115,
      "awayScore": 122,
      "excitement": 8.9,
      "breakdown": {
        "uncertainty": 9.296547403554516,
        "drama": 9.264598887388253,
        "finish": 5.23225877167531
      },
      "overtime": false,
      "bowlName": null,
      "playoffRound": null
    },
    {
      "id": "401810048",
      "homeTeam": "Magic",
      "awayTeam": "Celtics",
      "homeScore": 107,
      "awayScore": 111,
      "excitement": 8.8,
      "breakdown": {
        "uncertainty": 10,
        "drama": 8.429700809193175,
        "finish": 5.629746643598329
      },
      "overtime": false,
      "bowlName": null,
      "playoffRound": null
    },
    {
      "id": "401810050",
      "homeTeam": "76ers",
      "awayTeam": "Pistons",
      "homeScore": 108,
      "awayScore": 111,
      "excitement": 8,
      "breakdown": {
        "uncertainty": 9.510484714638611,
        "drama": 8.342417455310978,
        "finish": 4.058329665841704
      },
      "overtime": false,
      "bowlName": null,
      "playoffRound": null
    },
    {
      "id": "401810051",
      "homeTeam": "Warriors",
      "awayTeam": "Pacers",
      "homeScore": 114,
      "awayScore": 83,
      "excitement": 6.1,
      "breakdown": {
        "uncertainty": 5.199986443719866,
        "drama": 6.289278111061836,
        "finish": 4.877783834764557
      },
      "overtime": false,
      "bowlName": null,
      "playoffRound": null
    },
    {
      "id": "401810052",
      "homeTeam": "Kings",
      "awayTeam": "Timberwolves",
      "homeScore": 117,
      "awayScore": 144,
      "excitement": 3.4,
      "breakdown": {
        "uncertainty": 4.560491634703,
        "drama": 6.942425297969828,
        "finish": 0.9282821310314381
      },
      "overtime": false,
      "bowlName": null,
      "playoffRound": null
    },
    {
      "id": "401810047",
      "homeTeam": "Knicks",
      "awayTeam": "Nets",
      "homeScore": 134,
      "awayScore": 98,
      "excitement": 1.3,
      "breakdown": {
        "uncertainty": 0.9298292721348517,
        "drama": 0.6749524850627396,
        "finish": 0.44589015078990857
      },
      "overtime": false,
      "bowlName": null,
      "playoffRound": null
    }
  ],
  "metadata": {
    "sport": "NBA",
    "season": 2025,
    "count": 7,
    "totalGames": 7,
    "insufficientData": 0,
    "generatedAt": "2026-01-06T02:33:56.101Z",
    "source": "ESPN Win Probability Analysis",
    "date": "2025-11-09"
  }
}