{
  "success": true,
  "games": [
    {
      "id": "401810080",
      "homeTeam": "Cavaliers",
      "awayTeam": "Raptors",
      "homeScore": 113,
      "awayScore": 126,
      "excitement": 6.7,
      "breakdown": {
        "tension": 4.266213060018822,
        "drama": 7.6207780815133255,
        "finish": 4.584404837057329
      },
      "overtime": false,
      "bowlName": null,
      "playoffRound": null
    },
    {
      "id": "401810082",
      "homeTeam": "Jazz",
      "awayTeam": "Hawks",
      "homeScore": 122,
      "awayScore": 132,
      "excitement": 4.9,
      "breakdown": {
        "tension": 2.5,
        "drama": 4.700239661499791,
        "finish": 5.418642502880807
      },
      "overtime": false,
      "bowlName": null,
      "playoffRound": null
    },
    {
      "id": "401810081",
      "homeTeam": "Suns",
      "awayTeam": "Pacers",
      "homeScore": 133,
      "awayScore": 98,
      "excitement": 3.676785269906408,
      "breakdown": {
        "tension": 1.9202786925631061,
        "drama": 3.1347873082056297,
        "finish": 3.364893881747143
      },
      "overtime": false,
      "bowlName": null,
      "playoffRound": null
    }
  ],
  "metadata": {
    "sport": "NBA",
    "season": 2025,
    "count": 3,
    "totalGames": 3,
    "insufficientData": 0,
    "generatedAt": "2026-01-10T04:29:29.855Z",
    "algorithmVersion": "3.0",
    "source": "ESPN Win Probability Analysis",
    "date": "2025-11-13"
  }
}